{
  "type": "anaramus:cauldron_brewing",
  "activationIngredient": {
    "item": "minecraft:glass_bottle"
  },
  "consumeAllWater": false,
  "ingredients": [
    {
      "amount": 1,
      "ingredient": {
        "item": "minecraft:blaze_powder"
      }
    },
    {
      "amount": 1,
      "ingredient": {
        "item": "minecraft:nether_wart"
      }
    },
    {
      "amount": 3,
      "ingredient": {
        "item": "minecraft:redstone"
      }
    },
    {
      "amount": 2,
      "ingredient": {
        "item": "minecraft:ghast_tear"
      }
    },
    {
      "amount": 6,
      "ingredient": {
        "item": "minecraft:golden_carrot"
      }
    },
    {
      "amount": 1,
      "ingredient": {
        "item": "minecraft:hanging_roots"
      }
    },
    {
      "amount": 4,
      "ingredient": {
        "item": "minecraft:cocoa_beans"
      }
    },
    {
      "amount": 2,
      "ingredient": {
        "item": "minecraft:glow_berries"
      }
    },
    {
      "amount": 1,
      "ingredient": {
        "item": "minecraft:crimson_roots"
      }
    },
    {
      "amount": 1,
      "ingredient": {
        "item": "minecraft:gunpowder"
      }
    }
  ],
  "needsFire": true,
  "result": {
    "Count": 1,
    "id": "minecraft:splash_potion",
    "tag": {
      "CustomPotionColor": -65434,
      "HideFlags": 32,
      "custom_potion_effects": [
        {
          "ambient": 0,
          "amplifier": 4,
          "duration": 1,
          "id": "minecraft:instant_health",
          "show_icon": 1,
          "show_particles": 1
        }
      ],
      "display": {
        "Lore": [
          "{\"italic\":false,\"color\":\"blue\",\"translate\":\"potion.withAmplifier\",\"with\":[{\"translate\":\"effect.minecraft.instant_health\"},{\"translate\":\"potion.potency.4\"}]}"
        ],
        "Name": "{\"italic\":false,\"translate\":\"potions.anaramus.greater_healing\"}"
      }
    }
  }
}